{"FL_DATE":"2000-01-14","OP_CARRIER_FL_NUM":128,"ORIGIN_CITY_NAME":"Denver, CO","DEST":"PHL","DEST_CITY_NAME":"Philadelphia, PA","CRS_DEP_TIME":1300,"DEP_TIME":1257,"WHEELS_ON":1749,"TAXI_IN":38,"CRS_ARR_TIME":1817,"ARR_TIME":1827,"CANCELLED":0,"DISTANCE":1557}
{"FL_DATE":"2000-01-09","OP_CARRIER_FL_NUM":130,"ORIGIN_CITY_NAME":"Denver, CO","DEST":"PIT","DEST_CITY_NAME":"Pittsburgh, PA","CRS_DEP_TIME":800,"DEP_TIME":800,"WHEELS_ON":1232,"TAXI_IN":11,"CRS_ARR_TIME":1248,"ARR_TIME":1243,"CANCELLED":0,"DISTANCE":1290}
{"FL_DATE":"2000-01-06","OP_CARRIER_FL_NUM":132,"ORIGIN_CITY_NAME":"Denver, CO","DEST":"PIT","DEST_CITY_NAME":"Pittsburgh, PA","CRS_DEP_TIME":1033,"DEP_TIME":1029,"WHEELS_ON":1506,"TAXI_IN":6,"CRS_ARR_TIME":1524,"ARR_TIME":1512,"CANCELLED":0,"DISTANCE":1290}
{"FL_DATE":"2000-01-05","OP_CARRIER_FL_NUM":128,"ORIGIN_CITY_NAME":"Denver, CO","DEST":"PHL","DEST_CITY_NAME":"Philadelphia, PA","CRS_DEP_TIME":1300,"DEP_TIME":1301,"WHEELS_ON":1813,"TAXI_IN":5,"CRS_ARR_TIME":1817,"ARR_TIME":1818,"CANCELLED":0,"DISTANCE":1557}
{"FL_DATE":"2000-01-16","OP_CARRIER_FL_NUM":124,"ORIGIN_CITY_NAME":"Denver, CO","DEST":"CLT","DEST_CITY_NAME":"Charlotte, NC","CRS_DEP_TIME":1133,"DEP_TIME":1136,"WHEELS_ON":1621,"TAXI_IN":4,"CRS_ARR_TIME":1624,"ARR_TIME":1625,"CANCELLED":0,"DISTANCE":1338}
{"FL_DATE":"2000-01-14","OP_CARRIER_FL_NUM":124,"ORIGIN_CITY_NAME":"Denver, CO","DEST":"CLT","DEST_CITY_NAME":"Charlotte, NC","CRS_DEP_TIME":1133,"DEP_TIME":1140,"WHEELS_ON":1616,"TAXI_IN":4,"CRS_ARR_TIME":1624,"ARR_TIME":1620,"CANCELLED":0,"DISTANCE":1338}
{"FL_DATE":"2000-01-26","OP_CARRIER_FL_NUM":132,"ORIGIN_CITY_NAME":"Denver, CO","DEST":"PIT","DEST_CITY_NAME":"Pittsburgh, PA","CRS_DEP_TIME":1033,"DEP_TIME":1039,"WHEELS_ON":1531,"TAXI_IN":11,"CRS_ARR_TIME":1524,"ARR_TIME":1542,"CANCELLED":0,"DISTANCE":1290}
{"FL_DATE":"2000-01-20","OP_CARRIER_FL_NUM":136,"ORIGIN_CITY_NAME":"Denver, CO","DEST":"PIT","DEST_CITY_NAME":"Pittsburgh, PA","CRS_DEP_TIME":1630,"CRS_ARR_TIME":2118,"CANCELLED":1,"DISTANCE":1290}
{"FL_DATE":"2000-01-10","OP_CARRIER_FL_NUM":120,"ORIGIN_CITY_NAME":"Denver, CO","DEST":"CLT","DEST_CITY_NAME":"Charlotte, NC","CRS_DEP_TIME":1501,"DEP_TIME":1459,"WHEELS_ON":1935,"TAXI_IN":7,"CRS_ARR_TIME":1952,"ARR_TIME":1942,"CANCELLED":0,"DISTANCE":1338}
{"FL_DATE":"2000-01-27","OP_CARRIER_FL_NUM":120,"ORIGIN_CITY_NAME":"Denver, CO","DEST":"CLT","DEST_CITY_NAME":"Charlotte, NC","CRS_DEP_TIME":1501,"DEP_TIME":1500,"WHEELS_ON":1942,"TAXI_IN":5,"CRS_ARR_TIME":1952,"ARR_TIME":1947,"CANCELLED":0,"DISTANCE":1338}
{"FL_DATE":"2000-01-26","OP_CARRIER_FL_NUM":140,"ORIGIN_CITY_NAME":"Denver, CO","DEST":"PHL","DEST_CITY_NAME":"Philadelphia, PA","CRS_DEP_TIME":855,"DEP_TIME":916,"WHEELS_ON":1439,"TAXI_IN":8,"CRS_ARR_TIME":1409,"ARR_TIME":1447,"CANCELLED":0,"DISTANCE":1557}
{"FL_DATE":"2000-01-29","OP_CARRIER_FL_NUM":120,"ORIGIN_CITY_NAME":"Denver, CO","DEST":"CLT","DEST_CITY_NAME":"Charlotte, NC","CRS_DEP_TIME":1501,"DEP_TIME":1500,"WHEELS_ON":1948,"TAXI_IN":5,"CRS_ARR_TIME":1952,"ARR_TIME":1953,"CANCELLED":0,"DISTANCE":1338}
{"FL_DATE":"2000-01-25","OP_CARRIER_FL_NUM":130,"ORIGIN_CITY_NAME":"Denver, CO","DEST":"PIT","DEST_CITY_NAME":"Pittsburgh, PA","CRS_DEP_TIME":800,"DEP_TIME":757,"WHEELS_ON":1239,"TAXI_IN":7,"CRS_ARR_TIME":1248,"ARR_TIME":1246,"CANCELLED":0,"DISTANCE":1290}
{"FL_DATE":"2000-01-30","OP_CARRIER_FL_NUM":136,"ORIGIN_CITY_NAME":"Denver, CO","DEST":"PIT","DEST_CITY_NAME":"Pittsburgh, PA","CRS_DEP_TIME":1630,"DEP_TIME":1634,"WHEELS_ON":2118,"TAXI_IN":5,"CRS_ARR_TIME":2118,"ARR_TIME":2123,"CANCELLED":0,"DISTANCE":1290}
{"FL_DATE":"2000-01-25","OP_CARRIER_FL_NUM":124,"ORIGIN_CITY_NAME":"Denver, CO","DEST":"CLT","DEST_CITY_NAME":"Charlotte, NC","CRS_DEP_TIME":1133,"CRS_ARR_TIME":1624,"CANCELLED":1,"DISTANCE":1338}
{"FL_DATE":"2000-01-11","OP_CARRIER_FL_NUM":136,"ORIGIN_CITY_NAME":"Denver, CO","DEST":"PIT","DEST_CITY_NAME":"Pittsburgh, PA","CRS_DEP_TIME":1630,"DEP_TIME":1635,"WHEELS_ON":2112,"TAXI_IN":7,"CRS_ARR_TIME":2118,"ARR_TIME":2119,"CANCELLED":0,"DISTANCE":1290}
{"FL_DATE":"2000-01-09","OP_CARRIER_FL_NUM":120,"ORIGIN_CITY_NAME":"Denver, CO","DEST":"CLT","DEST_CITY_NAME":"Charlotte, NC","CRS_DEP_TIME":1501,"DEP_TIME":1505,"WHEELS_ON":1958,"TAXI_IN":7,"CRS_ARR_TIME":1952,"ARR_TIME":2005,"CANCELLED":0,"DISTANCE":1338}
{"FL_DATE":"2000-01-18","OP_CARRIER_FL_NUM":124,"ORIGIN_CITY_NAME":"Denver, CO","DEST":"CLT","DEST_CITY_NAME":"Charlotte, NC","CRS_DEP_TIME":1133,"DEP_TIME":1137,"WHEELS_ON":1618,"TAXI_IN":3,"CRS_ARR_TIME":1624,"ARR_TIME":1621,"CANCELLED":0,"DISTANCE":1338}
{"FL_DATE":"2000-01-29","OP_CARRIER_FL_NUM":132,"ORIGIN_CITY_NAME":"Denver, CO","DEST":"PIT","DEST_CITY_NAME":"Pittsburgh, PA","CRS_DEP_TIME":1033,"DEP_TIME":1029,"WHEELS_ON":1516,"TAXI_IN":5,"CRS_ARR_TIME":1524,"ARR_TIME":1521,"CANCELLED":0,"DISTANCE":1290}
{"FL_DATE":"2000-01-14","OP_CARRIER_FL_NUM":136,"ORIGIN_CITY_NAME":"Denver, CO","DEST":"PIT","DEST_CITY_NAME":"Pittsburgh, PA","CRS_DEP_TIME":1630,"DEP_TIME":1648,"WHEELS_ON":2128,"TAXI_IN":7,"CRS_ARR_TIME":2118,"ARR_TIME":2135,"CANCELLED":0,"DISTANCE":1290}
{"FL_DATE":"2000-01-13","OP_CARRIER_FL_NUM":130,"ORIGIN_CITY_NAME":"Denver, CO","DEST":"PIT","DEST_CITY_NAME":"Pittsburgh, PA","CRS_DEP_TIME":800,"DEP_TIME":757,"WHEELS_ON":1233,"TAXI_IN":8,"CRS_ARR_TIME":1248,"ARR_TIME":1241,"CANCELLED":0,"DISTANCE":1290}
{"FL_DATE":"2000-01-11","OP_CARRIER_FL_NUM":124,"ORIGIN_CITY_NAME":"Denver, CO","DEST":"CLT","DEST_CITY_NAME":"Charlotte, NC","CRS_DEP_TIME":1133,"DEP_TIME":1133,"WHEELS_ON":1613,"TAXI_IN":8,"CRS_ARR_TIME":1624,"ARR_TIME":1621,"CANCELLED":0,"DISTANCE":1338}
{"FL_DATE":"2000-01-03","OP_CARRIER_FL_NUM":132,"ORIGIN_CITY_NAME":"Denver, CO","DEST":"PIT","DEST_CITY_NAME":"Pittsburgh, PA","CRS_DEP_TIME":1033,"DEP_TIME":1030,"WHEELS_ON":1512,"TAXI_IN":7,"CRS_ARR_TIME":1524,"ARR_TIME":1519,"CANCELLED":0,"DISTANCE":1290}
{"FL_DATE":"2000-01-03","OP_CARRIER_FL_NUM":128,"ORIGIN_CITY_NAME":"Denver, CO","DEST":"PHL","DEST_CITY_NAME":"Philadelphia, PA","CRS_DEP_TIME":1300,"DEP_TIME":1300,"WHEELS_ON":1814,"TAXI_IN":11,"CRS_ARR_TIME":1817,"ARR_TIME":1825,"CANCELLED":0,"DISTANCE":1557}
{"FL_DATE":"2000-01-26","OP_CARRIER_FL_NUM":120,"ORIGIN_CITY_NAME":"Denver, CO","DEST":"CLT","DEST_CITY_NAME":"Charlotte, NC","CRS_DEP_TIME":1501,"DEP_TIME":1520,"WHEELS_ON":1956,"TAXI_IN":6,"CRS_ARR_TIME":1952,"ARR_TIME":2002,"CANCELLED":0,"DISTANCE":1338}
{"FL_DATE":"2000-01-29","OP_CARRIER_FL_NUM":140,"ORIGIN_CITY_NAME":"Denver, CO","DEST":"PHL","DEST_CITY_NAME":"Philadelphia, PA","CRS_DEP_TIME":855,"DEP_TIME":852,"WHEELS_ON":1428,"TAXI_IN":3,"CRS_ARR_TIME":1409,"ARR_TIME":1431,"CANCELLED":0,"DISTANCE":1557}
{"FL_DATE":"2000-01-18","OP_CARRIER_FL_NUM":128,"ORIGIN_CITY_NAME":"Denver, CO","DEST":"PHL","DEST_CITY_NAME":"Philadelphia, PA","CRS_DEP_TIME":1300,"DEP_TIME":1257,"WHEELS_ON":1801,"TAXI_IN":4,"CRS_ARR_TIME":1830,"ARR_TIME":1805,"CANCELLED":0,"DISTANCE":1557}
{"FL_DATE":"2000-01-19","OP_CARRIER_FL_NUM":136,"ORIGIN_CITY_NAME":"Denver, CO","DEST":"PIT","DEST_CITY_NAME":"Pittsburgh, PA","CRS_DEP_TIME":1630,"DEP_TIME":1629,"WHEELS_ON":2054,"TAXI_IN":6,"CRS_ARR_TIME":2118,"ARR_TIME":2100,"CANCELLED":0,"DISTANCE":1290}
{"FL_DATE":"2000-01-08","OP_CARRIER_FL_NUM":128,"ORIGIN_CITY_NAME":"Denver, CO","DEST":"PHL","DEST_CITY_NAME":"Philadelphia, PA","CRS_DEP_TIME":1300,"DEP_TIME":1304,"WHEELS_ON":1815,"TAXI_IN":5,"CRS_ARR_TIME":1817,"ARR_TIME":1820,"CANCELLED":0,"DISTANCE":1557}
{"FL_DATE":"2000-01-20","OP_CARRIER_FL_NUM":132,"ORIGIN_CITY_NAME":"Denver, CO","DEST":"PIT","DEST_CITY_NAME":"Pittsburgh, PA","CRS_DEP_TIME":1033,"DEP_TIME":1044,"WHEELS_ON":1518,"TAXI_IN":9,"CRS_ARR_TIME":1524,"ARR_TIME":1527,"CANCELLED":0,"DISTANCE":1290}
{"FL_DATE":"2000-01-07","OP_CARRIER_FL_NUM":140,"ORIGIN_CITY_NAME":"Denver, CO","DEST":"PHL","DEST_CITY_NAME":"Philadelphia, PA","CRS_DEP_TIME":855,"DEP_TIME":851,"WHEELS_ON":1400,"TAXI_IN":9,"CRS_ARR_TIME":1409,"ARR_TIME":1409,"CANCELLED":0,"DISTANCE":1557}
{"FL_DATE":"2000-01-06","OP_CARRIER_FL_NUM":136,"ORIGIN_CITY_NAME":"Denver, CO","DEST":"PIT","DEST_CITY_NAME":"Pittsburgh, PA","CRS_DEP_TIME":1630,"DEP_TIME":1629,"WHEELS_ON":2117,"TAXI_IN":6,"CRS_ARR_TIME":2118,"ARR_TIME":2123,"CANCELLED":0,"DISTANCE":1290}
{"FL_DATE":"2000-01-18","OP_CARRIER_FL_NUM":130,"ORIGIN_CITY_NAME":"Denver, CO","DEST":"PIT","DEST_CITY_NAME":"Pittsburgh, PA","CRS_DEP_TIME":800,"DEP_TIME":759,"WHEELS_ON":1231,"TAXI_IN":5,"CRS_ARR_TIME":1248,"ARR_TIME":1236,"CANCELLED":0,"DISTANCE":1290}
{"FL_DATE":"2000-01-09","OP_CARRIER_FL_NUM":136,"ORIGIN_CITY_NAME":"Denver, CO","DEST":"PIT","DEST_CITY_NAME":"Pittsburgh, PA","CRS_DEP_TIME":1630,"DEP_TIME":1637,"WHEELS_ON":2112,"TAXI_IN":7,"CRS_ARR_TIME":2118,"ARR_TIME":2119,"CANCELLED":0,"DISTANCE":1290}
{"FL_DATE":"2000-01-15","OP_CARRIER_FL_NUM":124,"ORIGIN_CITY_NAME":"Denver, CO","DEST":"CLT","DEST_CITY_NAME":"Charlotte, NC","CRS_DEP_TIME":1133,"DEP_TIME":1147,"WHEELS_ON":1624,"TAXI_IN":5,"CRS_ARR_TIME":1624,"ARR_TIME":1629,"CANCELLED":0,"DISTANCE":1338}
{"FL_DATE":"2000-01-20","OP_CARRIER_FL_NUM":130,"ORIGIN_CITY_NAME":"Denver, CO","DEST":"PIT","DEST_CITY_NAME":"Pittsburgh, PA","CRS_DEP_TIME":800,"DEP_TIME":758,"WHEELS_ON":1244,"TAXI_IN":12,"CRS_ARR_TIME":1248,"ARR_TIME":1256,"CANCELLED":0,"DISTANCE":1290}
{"FL_DATE":"2000-01-11","OP_CARRIER_FL_NUM":128,"ORIGIN_CITY_NAME":"Denver, CO","DEST":"PHL","DEST_CITY_NAME":"Philadelphia, PA","CRS_DEP_TIME":1300,"DEP_TIME":1259,"WHEELS_ON":1827,"TAXI_IN":5,"CRS_ARR_TIME":1817,"ARR_TIME":1832,"CANCELLED":0,"DISTANCE":1557}
{"FL_DATE":"2000-01-21","OP_CARRIER_FL_NUM":120,"ORIGIN_CITY_NAME":"Denver, CO","DEST":"CLT","DEST_CITY_NAME":"Charlotte, NC","CRS_DEP_TIME":1501,"DEP_TIME":1507,"WHEELS_ON":1934,"TAXI_IN":4,"CRS_ARR_TIME":1952,"ARR_TIME":1938,"CANCELLED":0,"DISTANCE":1338}
{"FL_DATE":"2000-01-15","OP_CARRIER_FL_NUM":136,"ORIGIN_CITY_NAME":"Denver, CO","DEST":"PIT","DEST_CITY_NAME":"Pittsburgh, PA","CRS_DEP_TIME":1630,"DEP_TIME":1627,"WHEELS_ON":2104,"TAXI_IN":6,"CRS_ARR_TIME":2118,"ARR_TIME":2110,"CANCELLED":0,"DISTANCE":1290}
{"FL_DATE":"2000-01-16","OP_CARRIER_FL_NUM":132,"ORIGIN_CITY_NAME":"Denver, CO","DEST":"PIT","DEST_CITY_NAME":"Pittsburgh, PA","CRS_DEP_TIME":1033,"DEP_TIME":1032,"WHEELS_ON":1506,"TAXI_IN":7,"CRS_ARR_TIME":1524,"ARR_TIME":1513,"CANCELLED":0,"DISTANCE":1290}
{"FL_DATE":"2000-01-15","OP_CARRIER_FL_NUM":140,"ORIGIN_CITY_NAME":"Denver, CO","DEST":"PHL","DEST_CITY_NAME":"Philadelphia, PA","CRS_DEP_TIME":855,"DEP_TIME":854,"WHEELS_ON":1406,"TAXI_IN":3,"CRS_ARR_TIME":1409,"ARR_TIME":1409,"CANCELLED":0,"DISTANCE":1557}
{"FL_DATE":"2000-01-22","OP_CARRIER_FL_NUM":136,"ORIGIN_CITY_NAME":"Denver, CO","DEST":"PIT","DEST_CITY_NAME":"Pittsburgh, PA","CRS_DEP_TIME":1630,"DEP_TIME":1625,"WHEELS_ON":2104,"TAXI_IN":7,"CRS_ARR_TIME":2118,"ARR_TIME":2111,"CANCELLED":0,"DISTANCE":1290}
{"FL_DATE":"2000-01-19","OP_CARRIER_FL_NUM":132,"ORIGIN_CITY_NAME":"Denver, CO","DEST":"PIT","DEST_CITY_NAME":"Pittsburgh, PA","CRS_DEP_TIME":1033,"DEP_TIME":1109,"WHEELS_ON":1536,"TAXI_IN":6,"CRS_ARR_TIME":1524,"ARR_TIME":1542,"CANCELLED":0,"DISTANCE":1290}
{"FL_DATE":"2000-01-22","OP_CARRIER_FL_NUM":128,"ORIGIN_CITY_NAME":"Denver, CO","DEST":"PHL","DEST_CITY_NAME":"Philadelphia, PA","CRS_DEP_TIME":1300,"DEP_TIME":1257,"WHEELS_ON":1804,"TAXI_IN":6,"CRS_ARR_TIME":1817,"ARR_TIME":1810,"CANCELLED":0,"DISTANCE":1557}
{"FL_DATE":"2000-01-12","OP_CARRIER_FL_NUM":140,"ORIGIN_CITY_NAME":"Denver, CO","DEST":"PHL","DEST_CITY_NAME":"Philadelphia, PA","CRS_DEP_TIME":855,"DEP_TIME":854,"WHEELS_ON":1345,"TAXI_IN":2,"CRS_ARR_TIME":1409,"ARR_TIME":1347,"CANCELLED":0,"DISTANCE":1557}
