{"FL_DATE":"2000-01-06","OP_CARRIER_FL_NUM":1236,"ORIGIN_CITY_NAME":"Scranton/Wilkes-Barre, PA","DEST":"PIT","DEST_CITY_NAME":"Pittsburgh, PA","CRS_DEP_TIME":920,"DEP_TIME":914,"WHEELS_ON":1015,"TAXI_IN":5,"CRS_ARR_TIME":1023,"ARR_TIME":1020,"CANCELLED":0,"DISTANCE":243}
{"FL_DATE":"2000-01-30","OP_CARRIER_FL_NUM":237,"ORIGIN_CITY_NAME":"Scranton/Wilkes-Barre, PA","DEST":"PHL","DEST_CITY_NAME":"Philadelphia, PA","CRS_DEP_TIME":642,"DEP_TIME":639,"WHEELS_ON":717,"TAXI_IN":4,"CRS_ARR_TIME":730,"ARR_TIME":721,"CANCELLED":0,"DISTANCE":105}
{"FL_DATE":"2000-01-29","OP_CARRIER_FL_NUM":205,"ORIGIN_CITY_NAME":"Scranton/Wilkes-Barre, PA","DEST":"PHL","DEST_CITY_NAME":"Philadelphia, PA","CRS_DEP_TIME":642,"DEP_TIME":644,"WHEELS_ON":721,"TAXI_IN":4,"CRS_ARR_TIME":730,"ARR_TIME":725,"CANCELLED":0,"DISTANCE":105}
{"FL_DATE":"2000-01-03","OP_CARRIER_FL_NUM":2005,"ORIGIN_CITY_NAME":"Scranton/Wilkes-Barre, PA","DEST":"PIT","DEST_CITY_NAME":"Pittsburgh, PA","CRS_DEP_TIME":1545,"DEP_TIME":1545,"WHEELS_ON":1653,"TAXI_IN":5,"CRS_ARR_TIME":1648,"ARR_TIME":1658,"CANCELLED":0,"DISTANCE":243}
{"FL_DATE":"2000-01-30","OP_CARRIER_FL_NUM":2005,"ORIGIN_CITY_NAME":"Scranton/Wilkes-Barre, PA","DEST":"PIT","DEST_CITY_NAME":"Pittsburgh, PA","CRS_DEP_TIME":1545,"DEP_TIME":1725,"WHEELS_ON":1822,"TAXI_IN":7,"CRS_ARR_TIME":1648,"ARR_TIME":1829,"CANCELLED":0,"DISTANCE":243}
{"FL_DATE":"2000-01-25","OP_CARRIER_FL_NUM":2005,"ORIGIN_CITY_NAME":"Scranton/Wilkes-Barre, PA","DEST":"PIT","DEST_CITY_NAME":"Pittsburgh, PA","CRS_DEP_TIME":1545,"CRS_ARR_TIME":1648,"CANCELLED":1,"DISTANCE":243}
{"FL_DATE":"2000-01-06","OP_CARRIER_FL_NUM":1965,"ORIGIN_CITY_NAME":"Scranton/Wilkes-Barre, PA","DEST":"PIT","DEST_CITY_NAME":"Pittsburgh, PA","CRS_DEP_TIME":1830,"DEP_TIME":1826,"WHEELS_ON":1930,"TAXI_IN":6,"CRS_ARR_TIME":1933,"ARR_TIME":1936,"CANCELLED":0,"DISTANCE":243}
{"FL_DATE":"2000-01-26","OP_CARRIER_FL_NUM":1965,"ORIGIN_CITY_NAME":"Scranton/Wilkes-Barre, PA","DEST":"PIT","DEST_CITY_NAME":"Pittsburgh, PA","CRS_DEP_TIME":1830,"DEP_TIME":1841,"WHEELS_ON":1944,"TAXI_IN":9,"CRS_ARR_TIME":1933,"ARR_TIME":1953,"CANCELLED":0,"DISTANCE":243}
{"FL_DATE":"2000-01-24","OP_CARRIER_FL_NUM":775,"ORIGIN_CITY_NAME":"Scranton/Wilkes-Barre, PA","DEST":"PIT","DEST_CITY_NAME":"Pittsburgh, PA","CRS_DEP_TIME":600,"DEP_TIME":557,"WHEELS_ON":656,"TAXI_IN":7,"CRS_ARR_TIME":703,"ARR_TIME":703,"CANCELLED":0,"DISTANCE":243}
{"FL_DATE":"2000-01-04","OP_CARRIER_FL_NUM":775,"ORIGIN_CITY_NAME":"Scranton/Wilkes-Barre, PA","DEST":"PIT","DEST_CITY_NAME":"Pittsburgh, PA","CRS_DEP_TIME":600,"DEP_TIME":555,"WHEELS_ON":710,"TAXI_IN":7,"CRS_ARR_TIME":703,"ARR_TIME":717,"CANCELLED":0,"DISTANCE":243}
{"FL_DATE":"2000-01-08","OP_CARRIER_FL_NUM":1564,"ORIGIN_CITY_NAME":"Scranton/Wilkes-Barre, PA","DEST":"PIT","DEST_CITY_NAME":"Pittsburgh, PA","CRS_DEP_TIME":1330,"DEP_TIME":1327,"WHEELS_ON":1421,"TAXI_IN":6,"CRS_ARR_TIME":1433,"ARR_TIME":1427,"CANCELLED":0,"DISTANCE":243}
{"FL_DATE":"2000-01-20","OP_CARRIER_FL_NUM":1965,"ORIGIN_CITY_NAME":"Scranton/Wilkes-Barre, PA","DEST":"PIT","DEST_CITY_NAME":"Pittsburgh, PA","CRS_DEP_TIME":1830,"DEP_TIME":1916,"WHEELS_ON":2011,"TAXI_IN":5,"CRS_ARR_TIME":1933,"ARR_TIME":2016,"CANCELLED":0,"DISTANCE":243}
{"FL_DATE":"2000-01-27","OP_CARRIER_FL_NUM":1236,"ORIGIN_CITY_NAME":"Scranton/Wilkes-Barre, PA","DEST":"PIT","DEST_CITY_NAME":"Pittsburgh, PA","CRS_DEP_TIME":920,"DEP_TIME":1115,"WHEELS_ON":1209,"TAXI_IN":5,"CRS_ARR_TIME":1023,"ARR_TIME":1214,"CANCELLED":0,"DISTANCE":243}
{"FL_DATE":"2000-01-25","OP_CARRIER_FL_NUM":1965,"ORIGIN_CITY_NAME":"Scranton/Wilkes-Barre, PA","DEST":"PIT","DEST_CITY_NAME":"Pittsburgh, PA","CRS_DEP_TIME":1830,"DEP_TIME":1930,"WHEELS_ON":2029,"TAXI_IN":13,"CRS_ARR_TIME":1933,"ARR_TIME":2042,"CANCELLED":0,"DISTANCE":243}
{"FL_DATE":"2000-01-11","OP_CARRIER_FL_NUM":1965,"ORIGIN_CITY_NAME":"Scranton/Wilkes-Barre, PA","DEST":"PIT","DEST_CITY_NAME":"Pittsburgh, PA","CRS_DEP_TIME":1830,"DEP_TIME":1828,"WHEELS_ON":1922,"TAXI_IN":7,"CRS_ARR_TIME":1933,"ARR_TIME":1929,"CANCELLED":0,"DISTANCE":243}
{"FL_DATE":"2000-01-19","OP_CARRIER_FL_NUM":2005,"ORIGIN_CITY_NAME":"Scranton/Wilkes-Barre, PA","DEST":"PIT","DEST_CITY_NAME":"Pittsburgh, PA","CRS_DEP_TIME":1545,"DEP_TIME":1539,"WHEELS_ON":1636,"TAXI_IN":5,"CRS_ARR_TIME":1648,"ARR_TIME":1641,"CANCELLED":0,"DISTANCE":243}
{"FL_DATE":"2000-01-28","OP_CARRIER_FL_NUM":205,"ORIGIN_CITY_NAME":"Scranton/Wilkes-Barre, PA","DEST":"PHL","DEST_CITY_NAME":"Philadelphia, PA","CRS_DEP_TIME":642,"DEP_TIME":653,"WHEELS_ON":732,"TAXI_IN":4,"CRS_ARR_TIME":730,"ARR_TIME":736,"CANCELLED":0,"DISTANCE":105}
{"FL_DATE":"2000-01-27","OP_CARRIER_FL_NUM":2005,"ORIGIN_CITY_NAME":"Scranton/Wilkes-Barre, PA","DEST":"PIT","DEST_CITY_NAME":"Pittsburgh, PA","CRS_DEP_TIME":1545,"DEP_TIME":1542,"WHEELS_ON":1639,"TAXI_IN":6,"CRS_ARR_TIME":1648,"ARR_TIME":1645,"CANCELLED":0,"DISTANCE":243}
{"FL_DATE":"2000-01-29","OP_CARRIER_FL_NUM":1236,"ORIGIN_CITY_NAME":"Scranton/Wilkes-Barre, PA","DEST":"PIT","DEST_CITY_NAME":"Pittsburgh, PA","CRS_DEP_TIME":920,"DEP_TIME":914,"WHEELS_ON":1009,"TAXI_IN":6,"CRS_ARR_TIME":1023,"ARR_TIME":1015,"CANCELLED":0,"DISTANCE":243}
{"FL_DATE":"2000-01-08","OP_CARRIER_FL_NUM":1965,"ORIGIN_CITY_NAME":"Scranton/Wilkes-Barre, PA","DEST":"PIT","DEST_CITY_NAME":"Pittsburgh, PA","CRS_DEP_TIME":1830,"DEP_TIME":1827,"WHEELS_ON":1919,"TAXI_IN":6,"CRS_ARR_TIME":1933,"ARR_TIME":1925,"CANCELLED":0,"DISTANCE":243}
{"FL_DATE":"2000-01-22","OP_CARRIER_FL_NUM":775,"ORIGIN_CITY_NAME":"Scranton/Wilkes-Barre, PA","DEST":"PIT","DEST_CITY_NAME":"Pittsburgh, PA","CRS_DEP_TIME":600,"DEP_TIME":558,"WHEELS_ON":659,"TAXI_IN":11,"CRS_ARR_TIME":703,"ARR_TIME":710,"CANCELLED":0,"DISTANCE":243}
{"FL_DATE":"2000-01-02","OP_CARRIER_FL_NUM":1236,"ORIGIN_CITY_NAME":"Scranton/Wilkes-Barre, PA","DEST":"PIT","DEST_CITY_NAME":"Pittsburgh, PA","CRS_DEP_TIME":920,"DEP_TIME":918,"WHEELS_ON":1011,"TAXI_IN":6,"CRS_ARR_TIME":1023,"ARR_TIME":1017,"CANCELLED":0,"DISTANCE":243}
{"FL_DATE":"2000-01-03","OP_CARRIER_FL_NUM":205,"ORIGIN_CITY_NAME":"Scranton/Wilkes-Barre, PA","DEST":"PHL","DEST_CITY_NAME":"Philadelphia, PA","CRS_DEP_TIME":642,"DEP_TIME":643,"WHEELS_ON":718,"TAXI_IN":4,"CRS_ARR_TIME":730,"ARR_TIME":722,"CANCELLED":0,"DISTANCE":105}
{"FL_DATE":"2000-01-20","OP_CARRIER_FL_NUM":775,"ORIGIN_CITY_NAME":"Scranton/Wilkes-Barre, PA","DEST":"PIT","DEST_CITY_NAME":"Pittsburgh, PA","CRS_DEP_TIME":600,"DEP_TIME":553,"WHEELS_ON":703,"TAXI_IN":6,"CRS_ARR_TIME":703,"ARR_TIME":709,"CANCELLED":0,"DISTANCE":243}
{"FL_DATE":"2000-01-30","OP_CARRIER_FL_NUM":775,"ORIGIN_CITY_NAME":"Scranton/Wilkes-Barre, PA","DEST":"PIT","DEST_CITY_NAME":"Pittsburgh, PA","CRS_DEP_TIME":600,"DEP_TIME":608,"WHEELS_ON":716,"TAXI_IN":11,"CRS_ARR_TIME":703,"ARR_TIME":727,"CANCELLED":0,"DISTANCE":243}
