{"FL_DATE":"2000-01-06","OP_CARRIER_FL_NUM":1563,"ORIGIN_CITY_NAME":"Baton Rouge, LA","DEST":"MEM","DEST_CITY_NAME":"Memphis, TN","CRS_DEP_TIME":1130,"DEP_TIME":1128,"WHEELS_ON":1223,"TAXI_IN":5,"CRS_ARR_TIME":1240,"ARR_TIME":1228,"CANCELLED":0,"DISTANCE":319}
{"FL_DATE":"2000-01-15","OP_CARRIER_FL_NUM":1563,"ORIGIN_CITY_NAME":"Baton Rouge, LA","DEST":"MEM","DEST_CITY_NAME":"Memphis, TN","CRS_DEP_TIME":1130,"DEP_TIME":1127,"WHEELS_ON":1229,"TAXI_IN":4,"CRS_ARR_TIME":1240,"ARR_TIME":1233,"CANCELLED":0,"DISTANCE":319}
{"FL_DATE":"2000-01-04","OP_CARRIER_FL_NUM":1544,"ORIGIN_CITY_NAME":"Baton Rouge, LA","DEST":"MEM","DEST_CITY_NAME":"Memphis, TN","CRS_DEP_TIME":1130,"DEP_TIME":1127,"WHEELS_ON":1234,"TAXI_IN":7,"CRS_ARR_TIME":1240,"ARR_TIME":1241,"CANCELLED":0,"DISTANCE":319}
{"FL_DATE":"2000-01-28","OP_CARRIER_FL_NUM":1035,"ORIGIN_CITY_NAME":"Baton Rouge, LA","DEST":"MEM","DEST_CITY_NAME":"Memphis, TN","CRS_DEP_TIME":630,"DEP_TIME":627,"WHEELS_ON":725,"TAXI_IN":5,"CRS_ARR_TIME":741,"ARR_TIME":730,"CANCELLED":0,"DISTANCE":319}
{"FL_DATE":"2000-01-31","OP_CARRIER_FL_NUM":1768,"ORIGIN_CITY_NAME":"Baton Rouge, LA","DEST":"MEM","DEST_CITY_NAME":"Memphis, TN","CRS_DEP_TIME":630,"DEP_TIME":637,"WHEELS_ON":830,"TAXI_IN":2,"CRS_ARR_TIME":741,"ARR_TIME":832,"CANCELLED":0,"DISTANCE":319}
{"FL_DATE":"2000-01-04","OP_CARRIER_FL_NUM":1548,"ORIGIN_CITY_NAME":"Baton Rouge, LA","DEST":"MEM","DEST_CITY_NAME":"Memphis, TN","CRS_DEP_TIME":630,"DEP_TIME":627,"WHEELS_ON":722,"TAXI_IN":4,"CRS_ARR_TIME":741,"ARR_TIME":726,"CANCELLED":0,"DISTANCE":319}
{"FL_DATE":"2000-01-23","OP_CARRIER_FL_NUM":1035,"ORIGIN_CITY_NAME":"Baton Rouge, LA","DEST":"MEM","DEST_CITY_NAME":"Memphis, TN","CRS_DEP_TIME":630,"DEP_TIME":623,"WHEELS_ON":729,"TAXI_IN":3,"CRS_ARR_TIME":741,"ARR_TIME":732,"CANCELLED":0,"DISTANCE":319}
{"FL_DATE":"2000-01-18","OP_CARRIER_FL_NUM":1035,"ORIGIN_CITY_NAME":"Baton Rouge, LA","DEST":"MEM","DEST_CITY_NAME":"Memphis, TN","CRS_DEP_TIME":630,"DEP_TIME":624,"WHEELS_ON":725,"TAXI_IN":4,"CRS_ARR_TIME":741,"ARR_TIME":729,"CANCELLED":0,"DISTANCE":319}
{"FL_DATE":"2000-01-25","OP_CARRIER_FL_NUM":972,"ORIGIN_CITY_NAME":"Baton Rouge, LA","DEST":"MEM","DEST_CITY_NAME":"Memphis, TN","CRS_DEP_TIME":1805,"DEP_TIME":1801,"WHEELS_ON":1910,"TAXI_IN":2,"CRS_ARR_TIME":1916,"ARR_TIME":1912,"CANCELLED":0,"DISTANCE":319}
{"FL_DATE":"2000-01-09","OP_CARRIER_FL_NUM":1035,"ORIGIN_CITY_NAME":"Baton Rouge, LA","DEST":"MEM","DEST_CITY_NAME":"Memphis, TN","CRS_DEP_TIME":630,"DEP_TIME":628,"WHEELS_ON":722,"TAXI_IN":2,"CRS_ARR_TIME":741,"ARR_TIME":724,"CANCELLED":0,"DISTANCE":319}
{"FL_DATE":"2000-01-21","OP_CARRIER_FL_NUM":972,"ORIGIN_CITY_NAME":"Baton Rouge, LA","DEST":"MEM","DEST_CITY_NAME":"Memphis, TN","CRS_DEP_TIME":1805,"DEP_TIME":1800,"WHEELS_ON":1903,"TAXI_IN":3,"CRS_ARR_TIME":1916,"ARR_TIME":1906,"CANCELLED":0,"DISTANCE":319}
{"FL_DATE":"2000-01-09","OP_CARRIER_FL_NUM":972,"ORIGIN_CITY_NAME":"Baton Rouge, LA","DEST":"MEM","DEST_CITY_NAME":"Memphis, TN","CRS_DEP_TIME":1805,"DEP_TIME":1800,"WHEELS_ON":1904,"TAXI_IN":7,"CRS_ARR_TIME":1916,"ARR_TIME":1911,"CANCELLED":0,"DISTANCE":319}
{"FL_DATE":"2000-01-19","OP_CARRIER_FL_NUM":1035,"ORIGIN_CITY_NAME":"Baton Rouge, LA","DEST":"MEM","DEST_CITY_NAME":"Memphis, TN","CRS_DEP_TIME":630,"DEP_TIME":627,"WHEELS_ON":725,"TAXI_IN":3,"CRS_ARR_TIME":741,"ARR_TIME":728,"CANCELLED":0,"DISTANCE":319}
{"FL_DATE":"2000-01-19","OP_CARRIER_FL_NUM":972,"ORIGIN_CITY_NAME":"Baton Rouge, LA","DEST":"MEM","DEST_CITY_NAME":"Memphis, TN","CRS_DEP_TIME":1805,"DEP_TIME":1801,"WHEELS_ON":1924,"TAXI_IN":3,"CRS_ARR_TIME":1916,"ARR_TIME":1927,"CANCELLED":0,"DISTANCE":319}
