{"FL_DATE":"2000-01-29","OP_CARRIER_FL_NUM":441,"ORIGIN_CITY_NAME":"Burbank, CA","DEST":"PDX","DEST_CITY_NAME":"Portland, OR","CRS_DEP_TIME":1417,"DEP_TIME":1417,"WHEELS_ON":1626,"TAXI_IN":2,"CRS_ARR_TIME":1633,"ARR_TIME":1628,"CANCELLED":0,"DISTANCE":817}
{"FL_DATE":"2000-01-19","OP_CARRIER_FL_NUM":421,"ORIGIN_CITY_NAME":"Burbank, CA","DEST":"SEA","DEST_CITY_NAME":"Seattle, WA","CRS_DEP_TIME":2052,"DEP_TIME":2105,"WHEELS_ON":2317,"TAXI_IN":3,"CRS_ARR_TIME":2321,"ARR_TIME":2320,"CANCELLED":0,"DISTANCE":937}
{"FL_DATE":"2000-01-18","OP_CARRIER_FL_NUM":419,"ORIGIN_CITY_NAME":"Burbank, CA","DEST":"PDX","DEST_CITY_NAME":"Portland, OR","CRS_DEP_TIME":1859,"DEP_TIME":1856,"WHEELS_ON":2056,"TAXI_IN":2,"CRS_ARR_TIME":2114,"ARR_TIME":2058,"CANCELLED":0,"DISTANCE":817}
{"FL_DATE":"2000-01-22","OP_CARRIER_FL_NUM":417,"ORIGIN_CITY_NAME":"Burbank, CA","DEST":"SEA","DEST_CITY_NAME":"Seattle, WA","CRS_DEP_TIME":1025,"DEP_TIME":1025,"WHEELS_ON":1255,"TAXI_IN":5,"CRS_ARR_TIME":1258,"ARR_TIME":1300,"CANCELLED":0,"DISTANCE":937}
{"FL_DATE":"2000-01-09","OP_CARRIER_FL_NUM":417,"ORIGIN_CITY_NAME":"Burbank, CA","DEST":"SEA","DEST_CITY_NAME":"Seattle, WA","CRS_DEP_TIME":1025,"DEP_TIME":1023,"WHEELS_ON":1300,"TAXI_IN":5,"CRS_ARR_TIME":1258,"ARR_TIME":1305,"CANCELLED":0,"DISTANCE":937}
{"FL_DATE":"2000-01-23","OP_CARRIER_FL_NUM":421,"ORIGIN_CITY_NAME":"Burbank, CA","DEST":"SEA","DEST_CITY_NAME":"Seattle, WA","CRS_DEP_TIME":2052,"DEP_TIME":2120,"WHEELS_ON":2335,"TAXI_IN":5,"CRS_ARR_TIME":2321,"ARR_TIME":2340,"CANCELLED":0,"DISTANCE":937}
{"FL_DATE":"2000-01-09","OP_CARRIER_FL_NUM":441,"ORIGIN_CITY_NAME":"Burbank, CA","DEST":"PDX","DEST_CITY_NAME":"Portland, OR","CRS_DEP_TIME":1417,"DEP_TIME":1415,"WHEELS_ON":1627,"TAXI_IN":3,"CRS_ARR_TIME":1633,"ARR_TIME":1630,"CANCELLED":0,"DISTANCE":817}
{"FL_DATE":"2000-01-14","OP_CARRIER_FL_NUM":441,"ORIGIN_CITY_NAME":"Burbank, CA","DEST":"PDX","DEST_CITY_NAME":"Portland, OR","CRS_DEP_TIME":1417,"DEP_TIME":1420,"WHEELS_ON":1614,"TAXI_IN":6,"CRS_ARR_TIME":1633,"ARR_TIME":1620,"CANCELLED":0,"DISTANCE":817}
{"FL_DATE":"2000-01-11","OP_CARRIER_FL_NUM":419,"ORIGIN_CITY_NAME":"Burbank, CA","DEST":"PDX","DEST_CITY_NAME":"Portland, OR","CRS_DEP_TIME":1859,"DEP_TIME":1854,"WHEELS_ON":2105,"TAXI_IN":9,"CRS_ARR_TIME":2114,"ARR_TIME":2114,"CANCELLED":0,"DISTANCE":817}
{"FL_DATE":"2000-01-05","OP_CARRIER_FL_NUM":417,"ORIGIN_CITY_NAME":"Burbank, CA","DEST":"SEA","DEST_CITY_NAME":"Seattle, WA","CRS_DEP_TIME":1025,"DEP_TIME":1025,"WHEELS_ON":1303,"TAXI_IN":6,"CRS_ARR_TIME":1258,"ARR_TIME":1309,"CANCELLED":0,"DISTANCE":937}
{"FL_DATE":"2000-01-28","OP_CARRIER_FL_NUM":417,"ORIGIN_CITY_NAME":"Burbank, CA","DEST":"SEA","DEST_CITY_NAME":"Seattle, WA","CRS_DEP_TIME":1025,"DEP_TIME":1110,"WHEELS_ON":1328,"TAXI_IN":5,"CRS_ARR_TIME":1258,"ARR_TIME":1333,"CANCELLED":0,"DISTANCE":937}
{"FL_DATE":"2000-01-18","OP_CARRIER_FL_NUM":435,"ORIGIN_CITY_NAME":"Burbank, CA","DEST":"PDX","DEST_CITY_NAME":"Portland, OR","CRS_DEP_TIME":655,"DEP_TIME":655,"WHEELS_ON":852,"TAXI_IN":4,"CRS_ARR_TIME":910,"ARR_TIME":856,"CANCELLED":0,"DISTANCE":817}
{"FL_DATE":"2000-01-02","OP_CARRIER_FL_NUM":417,"ORIGIN_CITY_NAME":"Burbank, CA","DEST":"SEA","DEST_CITY_NAME":"Seattle, WA","CRS_DEP_TIME":1025,"DEP_TIME":1025,"CRS_ARR_TIME":1258,"CANCELLED":0,"DISTANCE":937}
{"FL_DATE":"2000-01-03","OP_CARRIER_FL_NUM":417,"ORIGIN_CITY_NAME":"Burbank, CA","DEST":"SEA","DEST_CITY_NAME":"Seattle, WA","CRS_DEP_TIME":1025,"DEP_TIME":1031,"WHEELS_ON":1311,"TAXI_IN":28,"CRS_ARR_TIME":1258,"ARR_TIME":1339,"CANCELLED":0,"DISTANCE":937}
{"FL_DATE":"2000-01-14","OP_CARRIER_FL_NUM":567,"ORIGIN_CITY_NAME":"Burbank, CA","DEST":"SEA","DEST_CITY_NAME":"Seattle, WA","CRS_DEP_TIME":1637,"DEP_TIME":1724,"WHEELS_ON":1952,"TAXI_IN":5,"CRS_ARR_TIME":1900,"ARR_TIME":1957,"CANCELLED":0,"DISTANCE":937}
{"FL_DATE":"2000-01-06","OP_CARRIER_FL_NUM":435,"ORIGIN_CITY_NAME":"Burbank, CA","DEST":"PDX","DEST_CITY_NAME":"Portland, OR","CRS_DEP_TIME":655,"DEP_TIME":650,"WHEELS_ON":902,"TAXI_IN":2,"CRS_ARR_TIME":910,"ARR_TIME":904,"CANCELLED":0,"DISTANCE":817}
{"FL_DATE":"2000-01-31","OP_CARRIER_FL_NUM":567,"ORIGIN_CITY_NAME":"Burbank, CA","DEST":"SEA","DEST_CITY_NAME":"Seattle, WA","CRS_DEP_TIME":1637,"DEP_TIME":1636,"WHEELS_ON":1917,"TAXI_IN":6,"CRS_ARR_TIME":1900,"ARR_TIME":1923,"CANCELLED":0,"DISTANCE":937}
{"FL_DATE":"2000-01-26","OP_CARRIER_FL_NUM":441,"ORIGIN_CITY_NAME":"Burbank, CA","DEST":"PDX","DEST_CITY_NAME":"Portland, OR","CRS_DEP_TIME":1417,"DEP_TIME":1412,"WHEELS_ON":1612,"TAXI_IN":5,"CRS_ARR_TIME":1633,"ARR_TIME":1617,"CANCELLED":0,"DISTANCE":817}
{"FL_DATE":"2000-01-10","OP_CARRIER_FL_NUM":567,"ORIGIN_CITY_NAME":"Burbank, CA","DEST":"SEA","DEST_CITY_NAME":"Seattle, WA","CRS_DEP_TIME":1637,"DEP_TIME":1634,"WHEELS_ON":1909,"TAXI_IN":4,"CRS_ARR_TIME":1900,"ARR_TIME":1913,"CANCELLED":0,"DISTANCE":937}
{"FL_DATE":"2000-01-04","OP_CARRIER_FL_NUM":441,"ORIGIN_CITY_NAME":"Burbank, CA","DEST":"PDX","DEST_CITY_NAME":"Portland, OR","CRS_DEP_TIME":1417,"DEP_TIME":1424,"WHEELS_ON":1634,"TAXI_IN":4,"CRS_ARR_TIME":1633,"ARR_TIME":1638,"CANCELLED":0,"DISTANCE":817}
{"FL_DATE":"2000-01-29","OP_CARRIER_FL_NUM":567,"ORIGIN_CITY_NAME":"Burbank, CA","DEST":"SEA","DEST_CITY_NAME":"Seattle, WA","CRS_DEP_TIME":1637,"DEP_TIME":1632,"WHEELS_ON":1845,"TAXI_IN":7,"CRS_ARR_TIME":1900,"ARR_TIME":1852,"CANCELLED":0,"DISTANCE":937}
{"FL_DATE":"2000-01-13","OP_CARRIER_FL_NUM":421,"ORIGIN_CITY_NAME":"Burbank, CA","DEST":"SEA","DEST_CITY_NAME":"Seattle, WA","CRS_DEP_TIME":2052,"DEP_TIME":2107,"WHEELS_ON":2312,"TAXI_IN":3,"CRS_ARR_TIME":2321,"ARR_TIME":2315,"CANCELLED":0,"DISTANCE":937}
{"FL_DATE":"2000-01-28","OP_CARRIER_FL_NUM":567,"ORIGIN_CITY_NAME":"Burbank, CA","DEST":"SEA","DEST_CITY_NAME":"Seattle, WA","CRS_DEP_TIME":1637,"DEP_TIME":1639,"WHEELS_ON":1858,"TAXI_IN":7,"CRS_ARR_TIME":1900,"ARR_TIME":1905,"CANCELLED":0,"DISTANCE":937}
{"FL_DATE":"2000-01-30","OP_CARRIER_FL_NUM":441,"ORIGIN_CITY_NAME":"Burbank, CA","DEST":"PDX","DEST_CITY_NAME":"Portland, OR","CRS_DEP_TIME":1417,"DEP_TIME":1455,"WHEELS_ON":1700,"TAXI_IN":5,"CRS_ARR_TIME":1633,"ARR_TIME":1705,"CANCELLED":0,"DISTANCE":817}
{"FL_DATE":"2000-01-29","OP_CARRIER_FL_NUM":435,"ORIGIN_CITY_NAME":"Burbank, CA","DEST":"PDX","DEST_CITY_NAME":"Portland, OR","CRS_DEP_TIME":655,"DEP_TIME":650,"WHEELS_ON":851,"TAXI_IN":4,"CRS_ARR_TIME":910,"ARR_TIME":855,"CANCELLED":0,"DISTANCE":817}
