{"FL_DATE":"2000-01-13","OP_CARRIER_FL_NUM":1274,"ORIGIN_CITY_NAME":"Sioux Falls, SD","DEST":"MSP","DEST_CITY_NAME":"Minneapolis, MN","CRS_DEP_TIME":1645,"DEP_TIME":1642,"WHEELS_ON":1742,"TAXI_IN":3,"CRS_ARR_TIME":1751,"ARR_TIME":1745,"CANCELLED":0,"DISTANCE":197}
{"FL_DATE":"2000-01-12","OP_CARRIER_FL_NUM":217,"ORIGIN_CITY_NAME":"Sioux Falls, SD","DEST":"MSP","DEST_CITY_NAME":"Minneapolis, MN","CRS_DEP_TIME":645,"DEP_TIME":640,"WHEELS_ON":722,"TAXI_IN":5,"CRS_ARR_TIME":756,"ARR_TIME":727,"CANCELLED":0,"DISTANCE":197}
{"FL_DATE":"2000-01-14","OP_CARRIER_FL_NUM":1470,"ORIGIN_CITY_NAME":"Sioux Falls, SD","DEST":"MSP","DEST_CITY_NAME":"Minneapolis, MN","CRS_DEP_TIME":1300,"DEP_TIME":1258,"WHEELS_ON":1346,"TAXI_IN":4,"CRS_ARR_TIME":1357,"ARR_TIME":1350,"CANCELLED":0,"DISTANCE":197}
{"FL_DATE":"2000-01-30","OP_CARRIER_FL_NUM":738,"ORIGIN_CITY_NAME":"Sioux Falls, SD","DEST":"MSP","DEST_CITY_NAME":"Minneapolis, MN","CRS_DEP_TIME":525,"DEP_TIME":528,"WHEELS_ON":635,"TAXI_IN":8,"CRS_ARR_TIME":636,"ARR_TIME":643,"CANCELLED":0,"DISTANCE":197}
{"FL_DATE":"2000-01-24","OP_CARRIER_FL_NUM":1274,"ORIGIN_CITY_NAME":"Sioux Falls, SD","DEST":"MSP","DEST_CITY_NAME":"Minneapolis, MN","CRS_DEP_TIME":1645,"DEP_TIME":1641,"WHEELS_ON":1734,"TAXI_IN":5,"CRS_ARR_TIME":1751,"ARR_TIME":1739,"CANCELLED":0,"DISTANCE":197}
{"FL_DATE":"2000-01-21","OP_CARRIER_FL_NUM":217,"ORIGIN_CITY_NAME":"Sioux Falls, SD","DEST":"MSP","DEST_CITY_NAME":"Minneapolis, MN","CRS_DEP_TIME":645,"DEP_TIME":641,"WHEELS_ON":737,"TAXI_IN":4,"CRS_ARR_TIME":756,"ARR_TIME":741,"CANCELLED":0,"DISTANCE":197}
{"FL_DATE":"2000-01-10","OP_CARRIER_FL_NUM":764,"ORIGIN_CITY_NAME":"Sioux Falls, SD","DEST":"MSP","DEST_CITY_NAME":"Minneapolis, MN","CRS_DEP_TIME":1100,"DEP_TIME":1055,"WHEELS_ON":1152,"TAXI_IN":5,"CRS_ARR_TIME":1201,"ARR_TIME":1157,"CANCELLED":0,"DISTANCE":197}
{"FL_DATE":"2000-01-20","OP_CARRIER_FL_NUM":1470,"ORIGIN_CITY_NAME":"Sioux Falls, SD","DEST":"MSP","DEST_CITY_NAME":"Minneapolis, MN","CRS_DEP_TIME":1300,"DEP_TIME":1257,"WHEELS_ON":1343,"TAXI_IN":3,"CRS_ARR_TIME":1357,"ARR_TIME":1346,"CANCELLED":0,"DISTANCE":197}
{"FL_DATE":"2000-01-13","OP_CARRIER_FL_NUM":764,"ORIGIN_CITY_NAME":"Sioux Falls, SD","DEST":"MSP","DEST_CITY_NAME":"Minneapolis, MN","CRS_DEP_TIME":1100,"DEP_TIME":1056,"WHEELS_ON":1147,"TAXI_IN":5,"CRS_ARR_TIME":1201,"ARR_TIME":1152,"CANCELLED":0,"DISTANCE":197}
{"FL_DATE":"2000-01-11","OP_CARRIER_FL_NUM":1597,"ORIGIN_CITY_NAME":"Sioux Falls, SD","DEST":"MSP","DEST_CITY_NAME":"Minneapolis, MN","CRS_DEP_TIME":1835,"DEP_TIME":1829,"WHEELS_ON":1918,"TAXI_IN":5,"CRS_ARR_TIME":1935,"ARR_TIME":1923,"CANCELLED":0,"DISTANCE":197}
{"FL_DATE":"2000-01-18","OP_CARRIER_FL_NUM":1470,"ORIGIN_CITY_NAME":"Sioux Falls, SD","DEST":"MSP","DEST_CITY_NAME":"Minneapolis, MN","CRS_DEP_TIME":1300,"DEP_TIME":1255,"WHEELS_ON":1337,"TAXI_IN":4,"CRS_ARR_TIME":1357,"ARR_TIME":1341,"CANCELLED":0,"DISTANCE":197}
{"FL_DATE":"2000-01-23","OP_CARRIER_FL_NUM":738,"ORIGIN_CITY_NAME":"Sioux Falls, SD","DEST":"MSP","DEST_CITY_NAME":"Minneapolis, MN","CRS_DEP_TIME":525,"DEP_TIME":523,"WHEELS_ON":608,"TAXI_IN":7,"CRS_ARR_TIME":636,"ARR_TIME":615,"CANCELLED":0,"DISTANCE":197}
{"FL_DATE":"2000-01-03","OP_CARRIER_FL_NUM":738,"ORIGIN_CITY_NAME":"Sioux Falls, SD","DEST":"MSP","DEST_CITY_NAME":"Minneapolis, MN","CRS_DEP_TIME":530,"DEP_TIME":526,"WHEELS_ON":612,"TAXI_IN":6,"CRS_ARR_TIME":638,"ARR_TIME":618,"CANCELLED":0,"DISTANCE":197}
{"FL_DATE":"2000-01-08","OP_CARRIER_FL_NUM":1597,"ORIGIN_CITY_NAME":"Sioux Falls, SD","DEST":"MSP","DEST_CITY_NAME":"Minneapolis, MN","CRS_DEP_TIME":1835,"DEP_TIME":1833,"WHEELS_ON":1933,"TAXI_IN":5,"CRS_ARR_TIME":1935,"ARR_TIME":1938,"CANCELLED":0,"DISTANCE":197}
{"FL_DATE":"2000-01-25","OP_CARRIER_FL_NUM":1274,"ORIGIN_CITY_NAME":"Sioux Falls, SD","DEST":"MSP","DEST_CITY_NAME":"Minneapolis, MN","CRS_DEP_TIME":1645,"DEP_TIME":1641,"WHEELS_ON":1736,"TAXI_IN":4,"CRS_ARR_TIME":1751,"ARR_TIME":1740,"CANCELLED":0,"DISTANCE":197}
{"FL_DATE":"2000-01-16","OP_CARRIER_FL_NUM":738,"ORIGIN_CITY_NAME":"Sioux Falls, SD","DEST":"MSP","DEST_CITY_NAME":"Minneapolis, MN","CRS_DEP_TIME":525,"DEP_TIME":523,"WHEELS_ON":604,"TAXI_IN":13,"CRS_ARR_TIME":636,"ARR_TIME":617,"CANCELLED":0,"DISTANCE":197}
{"FL_DATE":"2000-01-11","OP_CARRIER_FL_NUM":1470,"ORIGIN_CITY_NAME":"Sioux Falls, SD","DEST":"MSP","DEST_CITY_NAME":"Minneapolis, MN","CRS_DEP_TIME":1300,"DEP_TIME":1253,"WHEELS_ON":1338,"TAXI_IN":3,"CRS_ARR_TIME":1357,"ARR_TIME":1341,"CANCELLED":0,"DISTANCE":197}
{"FL_DATE":"2000-01-14","OP_CARRIER_FL_NUM":764,"ORIGIN_CITY_NAME":"Sioux Falls, SD","DEST":"MSP","DEST_CITY_NAME":"Minneapolis, MN","CRS_DEP_TIME":1100,"DEP_TIME":1056,"WHEELS_ON":1150,"TAXI_IN":7,"CRS_ARR_TIME":1201,"ARR_TIME":1157,"CANCELLED":0,"DISTANCE":197}
{"FL_DATE":"2000-01-23","OP_CARRIER_FL_NUM":1274,"ORIGIN_CITY_NAME":"Sioux Falls, SD","DEST":"MSP","DEST_CITY_NAME":"Minneapolis, MN","CRS_DEP_TIME":1645,"DEP_TIME":1652,"WHEELS_ON":1800,"TAXI_IN":6,"CRS_ARR_TIME":1751,"ARR_TIME":1806,"CANCELLED":0,"DISTANCE":197}
{"FL_DATE":"2000-01-05","OP_CARRIER_FL_NUM":1597,"ORIGIN_CITY_NAME":"Sioux Falls, SD","DEST":"MSP","DEST_CITY_NAME":"Minneapolis, MN","CRS_DEP_TIME":1835,"DEP_TIME":1927,"WHEELS_ON":2020,"TAXI_IN":7,"CRS_ARR_TIME":1935,"ARR_TIME":2027,"CANCELLED":0,"DISTANCE":197}
{"FL_DATE":"2000-01-26","OP_CARRIER_FL_NUM":217,"ORIGIN_CITY_NAME":"Sioux Falls, SD","DEST":"MSP","DEST_CITY_NAME":"Minneapolis, MN","CRS_DEP_TIME":645,"DEP_TIME":640,"WHEELS_ON":734,"TAXI_IN":4,"CRS_ARR_TIME":756,"ARR_TIME":738,"CANCELLED":0,"DISTANCE":197}
{"FL_DATE":"2000-01-23","OP_CARRIER_FL_NUM":1597,"ORIGIN_CITY_NAME":"Sioux Falls, SD","DEST":"MSP","DEST_CITY_NAME":"Minneapolis, MN","CRS_DEP_TIME":1835,"DEP_TIME":1825,"WHEELS_ON":1914,"TAXI_IN":5,"CRS_ARR_TIME":1935,"ARR_TIME":1919,"CANCELLED":0,"DISTANCE":197}
{"FL_DATE":"2000-01-10","OP_CARRIER_FL_NUM":1470,"ORIGIN_CITY_NAME":"Sioux Falls, SD","DEST":"MSP","DEST_CITY_NAME":"Minneapolis, MN","CRS_DEP_TIME":1300,"DEP_TIME":1254,"WHEELS_ON":1340,"TAXI_IN":6,"CRS_ARR_TIME":1357,"ARR_TIME":1346,"CANCELLED":0,"DISTANCE":197}
{"FL_DATE":"2000-01-13","OP_CARRIER_FL_NUM":1470,"ORIGIN_CITY_NAME":"Sioux Falls, SD","DEST":"MSP","DEST_CITY_NAME":"Minneapolis, MN","CRS_DEP_TIME":1300,"DEP_TIME":1254,"WHEELS_ON":1337,"TAXI_IN":3,"CRS_ARR_TIME":1357,"ARR_TIME":1340,"CANCELLED":0,"DISTANCE":197}
{"FL_DATE":"2000-01-02","OP_CARRIER_FL_NUM":136,"ORIGIN_CITY_NAME":"Sioux Falls, SD","DEST":"MSP","DEST_CITY_NAME":"Minneapolis, MN","CRS_DEP_TIME":1300,"DEP_TIME":1256,"WHEELS_ON":1339,"TAXI_IN":3,"CRS_ARR_TIME":1356,"ARR_TIME":1342,"CANCELLED":0,"DISTANCE":197}
{"FL_DATE":"2000-01-19","OP_CARRIER_FL_NUM":738,"ORIGIN_CITY_NAME":"Sioux Falls, SD","DEST":"MSP","DEST_CITY_NAME":"Minneapolis, MN","CRS_DEP_TIME":525,"DEP_TIME":522,"WHEELS_ON":640,"TAXI_IN":3,"CRS_ARR_TIME":636,"ARR_TIME":643,"CANCELLED":0,"DISTANCE":197}
{"FL_DATE":"2000-01-24","OP_CARRIER_FL_NUM":1597,"ORIGIN_CITY_NAME":"Sioux Falls, SD","DEST":"MSP","DEST_CITY_NAME":"Minneapolis, MN","CRS_DEP_TIME":1835,"DEP_TIME":1831,"WHEELS_ON":1924,"TAXI_IN":6,"CRS_ARR_TIME":1935,"ARR_TIME":1930,"CANCELLED":0,"DISTANCE":197}
{"FL_DATE":"2000-01-28","OP_CARRIER_FL_NUM":1470,"ORIGIN_CITY_NAME":"Sioux Falls, SD","DEST":"MSP","DEST_CITY_NAME":"Minneapolis, MN","CRS_DEP_TIME":1300,"DEP_TIME":1254,"WHEELS_ON":1352,"TAXI_IN":3,"CRS_ARR_TIME":1357,"ARR_TIME":1355,"CANCELLED":0,"DISTANCE":197}
{"FL_DATE":"2000-01-27","OP_CARRIER_FL_NUM":738,"ORIGIN_CITY_NAME":"Sioux Falls, SD","DEST":"MSP","DEST_CITY_NAME":"Minneapolis, MN","CRS_DEP_TIME":525,"DEP_TIME":520,"WHEELS_ON":606,"TAXI_IN":21,"CRS_ARR_TIME":636,"ARR_TIME":627,"CANCELLED":0,"DISTANCE":197}
{"FL_DATE":"2000-01-21","OP_CARRIER_FL_NUM":738,"ORIGIN_CITY_NAME":"Sioux Falls, SD","DEST":"MSP","DEST_CITY_NAME":"Minneapolis, MN","CRS_DEP_TIME":525,"DEP_TIME":520,"WHEELS_ON":618,"TAXI_IN":6,"CRS_ARR_TIME":636,"ARR_TIME":624,"CANCELLED":0,"DISTANCE":197}
{"FL_DATE":"2000-01-08","OP_CARRIER_FL_NUM":1470,"ORIGIN_CITY_NAME":"Sioux Falls, SD","DEST":"MSP","DEST_CITY_NAME":"Minneapolis, MN","CRS_DEP_TIME":1300,"DEP_TIME":1254,"WHEELS_ON":1334,"TAXI_IN":3,"CRS_ARR_TIME":1357,"ARR_TIME":1337,"CANCELLED":0,"DISTANCE":197}
{"FL_DATE":"2000-01-25","OP_CARRIER_FL_NUM":217,"ORIGIN_CITY_NAME":"Sioux Falls, SD","DEST":"MSP","DEST_CITY_NAME":"Minneapolis, MN","CRS_DEP_TIME":645,"DEP_TIME":643,"WHEELS_ON":737,"TAXI_IN":3,"CRS_ARR_TIME":756,"ARR_TIME":740,"CANCELLED":0,"DISTANCE":197}
{"FL_DATE":"2000-01-29","OP_CARRIER_FL_NUM":1274,"ORIGIN_CITY_NAME":"Sioux Falls, SD","DEST":"MSP","DEST_CITY_NAME":"Minneapolis, MN","CRS_DEP_TIME":1645,"DEP_TIME":1639,"WHEELS_ON":1740,"TAXI_IN":5,"CRS_ARR_TIME":1751,"ARR_TIME":1745,"CANCELLED":0,"DISTANCE":197}
{"FL_DATE":"2000-01-30","OP_CARRIER_FL_NUM":1470,"ORIGIN_CITY_NAME":"Sioux Falls, SD","DEST":"MSP","DEST_CITY_NAME":"Minneapolis, MN","CRS_DEP_TIME":1300,"DEP_TIME":1255,"WHEELS_ON":1342,"TAXI_IN":4,"CRS_ARR_TIME":1357,"ARR_TIME":1346,"CANCELLED":0,"DISTANCE":197}
